geokey_duplicate/__init__.py
geokey_duplicate/base.py
geokey_duplicate/models.py
geokey_duplicate/renderers.py
geokey_duplicate/urls.py
geokey_duplicate/utils.py
geokey_duplicate/views.py
geokey_duplicate/migrations/0001_initial.py
geokey_duplicate/migrations/__init__.py
geokey_duplicate/static/js/admin.ui.duplicate.js
geokey_duplicate/templates/duplicate_header.html
geokey_duplicate/templates/duplicate_index.html
geokey_duplicate/templatetags/__init__.py
travis_ci/__init__.py
travis_ci/manage.py
travis_ci/settings.py
travis_ci/wsgi.py
geokey_duplicate-0.0.4.dist-info/LICENSE
geokey_duplicate-0.0.4.dist-info/METADATA
geokey_duplicate-0.0.4.dist-info/WHEEL
geokey_duplicate-0.0.4.dist-info/top_level.txt
geokey_duplicate-0.0.4.dist-info/RECORD
