Metadata-Version: 2.1
Name: geokey-duplicate
Version: 0.0.4
Summary: Duplicate projects and categories
Home-page: https://github.com/ExCiteS/geokey-duplicate
Author: Francisco Sanz
Author-email: frasanz@bifi.es
License: MIT
Download-URL: https://github.com/ExCiteS/geokey-duplicate/tarball/0.0.4
Platform: UNKNOWN
